Bicimad/BiciMad.py
Bicimad/UrlEMT.py
Bicimad/__init__.py
Bicimad/utils.py
my_BiciMad_Project-0.0.1.dist-info/LICENSE.txt
my_BiciMad_Project-0.0.1.dist-info/METADATA
my_BiciMad_Project-0.0.1.dist-info/WHEEL
my_BiciMad_Project-0.0.1.dist-info/top_level.txt
my_BiciMad_Project-0.0.1.dist-info/RECORD
