Metadata-Version: 2.1
Name: my_BiciMad_Project
Version: 0.0.1
License: MIT License
Requires-Python: >=3.11
License-File: LICENSE.txt
Requires-Dist: requests>=2.24.0
Requires-Dist: pandas>=2.2.3
